AWSSignV4/__init__.py
AWSSignV4/__version__.py
AWSSignV4/client.py
AWSSignV4/signv4.py
tests/__init__.py
tests/test_client.py
AWSSignV4-0.0.8.dist-info/LICENSE
AWSSignV4-0.0.8.dist-info/METADATA
AWSSignV4-0.0.8.dist-info/WHEEL
AWSSignV4-0.0.8.dist-info/top_level.txt
AWSSignV4-0.0.8.dist-info/RECORD
