Metadata-Version: 2.1
Name: AWSSignV4
Version: 0.0.8
Summary: This package will help to use AWS service without SDK
Home-page: https://github.com/vubon/AWSSignV4
Author: Vubon Roy
Author-email: vubon.roy@gmail.com
License: MIT
Project-URL: Documentation, https://github.com/vubon/AWSSignV4/blob/master/docs/GUIDE.md
Platform: Python
Classifier: License :: OSI Approved :: MIT License
Classifier: Environment :: Web Environment
Classifier: Intended Audience :: Developers
Classifier: Programming Language :: Python :: 3 :: Only
Classifier: Programming Language :: Python :: 3.6
Classifier: Programming Language :: Python :: 3.7
Classifier: Programming Language :: Python :: 3.8
Classifier: Programming Language :: Python :: 3.9
Classifier: Operating System :: OS Independent
Classifier: Natural Language :: English
Classifier: Topic :: Software Development :: Libraries :: Python Modules
Requires-Dist: requests
